ExtendedMainframe3270/__init__.py
ExtendedMainframe3270/py3270.py
ExtendedMainframe3270/version.py
ExtendedMainframe3270/x3270.py
robotframework_mainframe3270_extended-1.2.2.dist-info/LICENSE.md
robotframework_mainframe3270_extended-1.2.2.dist-info/METADATA
robotframework_mainframe3270_extended-1.2.2.dist-info/WHEEL
robotframework_mainframe3270_extended-1.2.2.dist-info/top_level.txt
robotframework_mainframe3270_extended-1.2.2.dist-info/RECORD
