Metadata-Version: 2.1
Name: robotframework-mainframe3270-extended
Version: 1.2.2
Summary: Extended Mainframe Test library for Robot Framework based on Altran's library
Home-page: https://github.com/otemek/robotframework-mainframe3270
Author: tom bsc
Author-email: tom.bsc@outlook.com
License: MIT License
Platform: UNKNOWN
Requires: robotframework
Requires: six
Requires: imgkit
Requires-Python: >=3
